gfsubsets/__init__.py
gfsubsets/_version.py
gfsubsets/subsets.py
gfsubsets/data/adlam_unique-glyphs.nam
gfsubsets/data/ahom_unique-glyphs.nam
gfsubsets/data/anatolian-hieroglyphs_unique-glyphs.nam
gfsubsets/data/arabic_unique-glyphs.nam
gfsubsets/data/armenian_unique-glyphs.nam
gfsubsets/data/avestan_unique-glyphs.nam
gfsubsets/data/balinese_unique-glyphs.nam
gfsubsets/data/bamum_unique-glyphs.nam
gfsubsets/data/bassa-vah_unique-glyphs.nam
gfsubsets/data/batak_unique-glyphs.nam
gfsubsets/data/bengali_unique-glyphs.nam
gfsubsets/data/beria-erfe_unique-glyphs.nam
gfsubsets/data/bhaiksuki_unique-glyphs.nam
gfsubsets/data/brahmi_unique-glyphs.nam
gfsubsets/data/braille_unique-glyphs.nam
gfsubsets/data/buginese_unique-glyphs.nam
gfsubsets/data/buhid_unique-glyphs.nam
gfsubsets/data/canadian-aboriginal_unique-glyphs.nam
gfsubsets/data/carian_unique-glyphs.nam
gfsubsets/data/caucasian-albanian_unique-glyphs.nam
gfsubsets/data/chakma_unique-glyphs.nam
gfsubsets/data/cham_unique-glyphs.nam
gfsubsets/data/cherokee_unique-glyphs.nam
gfsubsets/data/chinese-hongkong_unique-glyphs.nam
gfsubsets/data/chinese-simplified_unique-glyphs.nam
gfsubsets/data/chinese-traditional_unique-glyphs.nam
gfsubsets/data/chorasmian_unique-glyphs.nam
gfsubsets/data/coptic_unique-glyphs.nam
gfsubsets/data/cuneiform_unique-glyphs.nam
gfsubsets/data/cypriot_unique-glyphs.nam
gfsubsets/data/cypro-minoan_unique-glyphs.nam
gfsubsets/data/cyrillic-ext_unique-glyphs.nam
gfsubsets/data/cyrillic_unique-glyphs.nam
gfsubsets/data/deseret_unique-glyphs.nam
gfsubsets/data/devanagari_unique-glyphs.nam
gfsubsets/data/dives-akuru_unique-glyphs.nam
gfsubsets/data/dogra_unique-glyphs.nam
gfsubsets/data/duployan_unique-glyphs.nam
gfsubsets/data/egyptian-hieroglyphs_unique-glyphs.nam
gfsubsets/data/elbasan_unique-glyphs.nam
gfsubsets/data/elymaic_unique-glyphs.nam
gfsubsets/data/ethiopic_unique-glyphs.nam
gfsubsets/data/garay_unique-glyphs.nam
gfsubsets/data/georgian_unique-glyphs.nam
gfsubsets-2025.11.4.dist-info/licenses/LICENSE
gfsubsets-2025.11.4.dist-info/METADATA
gfsubsets-2025.11.4.dist-info/WHEEL
gfsubsets-2025.11.4.dist-info/top_level.txt
gfsubsets-2025.11.4.dist-info/RECORD
