Metadata-Version: 2.4
Name: gfsubsets
Version: 2025.11.4
Summary: Codepoint definitions for the Google Fonts subsetter
Author-email: Dave Crossland <dave@lab6.com>, Lasse Fister <lasse@graphicore.de>, Marc Foley <m.foley.88@gmail.com>, Simon Cozens <simon@simon-cozens.org>, Garret Rieger <grieger@google.com>, Roderick Sheeter <rsheeter@google.com>
License:                                  Apache License
License-File: LICENSE
Requires-Dist: importlib_resources
Provides-Extra: dev
Requires-Dist: youseedee; extra == "dev"
Dynamic: license-file
